heimdall/__init__.py
heimdall/cdbg_native.cpython-310-darwin.so
heimdall/configure_autoinstrumentation.py
heimdall/application/__init__.py
heimdall/application/application.py
heimdall/application/application_info_provider.py
heimdall/application/config_aware_application_info_provider.py
heimdall/application/utils.py
heimdall/broker/__init__.py
heimdall/broker/broker_client.py
heimdall/broker/broker_credentials.py
heimdall/broker/broker_manager.py
heimdall/broker/broker_message_callback.py
heimdall/broker/ws_app.py
heimdall/broker/application/__init__.py
heimdall/broker/application/application_filter.py
heimdall/broker/application/application_status.py
heimdall/broker/application/application_status_provider.py
heimdall/broker/event/__init__.py
heimdall/broker/event/application_status_event.py
heimdall/broker/event/base_event.py
heimdall/broker/event/event.py
heimdall/broker/handler/__init__.py
heimdall/broker/handler/request/__init__.py
heimdall/broker/handler/request/request_handler.py
heimdall/broker/handler/response/__init__.py
heimdall/broker/handler/response/response_handler.py
heimdall/broker/request/__init__.py
heimdall/broker/request/base_request.py
heimdall/broker/request/filter_logpoints_request.py
heimdall/broker/request/filter_tracepoints_request.py
heimdall/broker/request/get_config_request.py
heimdall/broker/request/request.py
heimdall/broker/response/__init__.py
heimdall/broker/response/base_response.py
heimdall/broker/response/response.py
heimdall/config/__init__.py
heimdall/config/config_metadata.py
heimdall/config/config_names.py
heimdall/config/config_provider.py
heimdall/config/constants.py
heimdall/external/__init__.py
heimdall/external/googleclouddebugger/__init__.py
heimdall/external/googleclouddebugger/breakpoints_manager.py
heimdall/external/googleclouddebugger/bytecode_breakpoint.cc
heimdall/external/googleclouddebugger/bytecode_manipulator.cc
heimdall/external/googleclouddebugger/collector.py
ctrlb_heimdall-1.0.8.dist-info/LICENSE
ctrlb_heimdall-1.0.8.dist-info/METADATA
ctrlb_heimdall-1.0.8.dist-info/WHEEL
ctrlb_heimdall-1.0.8.dist-info/top_level.txt
ctrlb_heimdall-1.0.8.dist-info/RECORD
