Metadata-Version: 2.1
Name: ctrlb-heimdall
Version: 1.0.8
Summary: CtrlB Python Debugger
Home-page: https://ctrlb.ai
Author: Mayank
Author-email: mayank@ctrlb.ai
Classifier: Development Status :: 5 - Production/Stable
Classifier: Intended Audience :: Developers
Classifier: Intended Audience :: System Administrators
Classifier: Programming Language :: Python :: 3.7
Classifier: Programming Language :: Python :: 3.8
Classifier: Programming Language :: Python :: 3.9
Classifier: Programming Language :: Python :: 3.10
Requires-Python: !=3.0.*, !=3.1.*, !=3.2.*, !=3.3.*, !=3.4.*, !=3.5.*, !=3.6.*
License-File: LICENSE
Requires-Dist: six >=1.11
Requires-Dist: websocket-client >=0.56.0
Requires-Dist: pystache >=0.6.0
Requires-Dist: cachetools >=5.2.0
Requires-Dist: opentelemetry-api ~=1.5
Requires-Dist: opentelemetry-sdk ~=1.13
Requires-Dist: opentelemetry-distro ==0.39b0
Requires-Dist: importlib-metadata ==6.0
Requires-Dist: opentelemetry-instrumentation-aio-pika ==0.39b0
Requires-Dist: opentelemetry-instrumentation-aiohttp-client ==0.39b0
Requires-Dist: opentelemetry-instrumentation-aiopg ==0.39b0
Requires-Dist: opentelemetry-instrumentation-asgi ==0.39b0
Requires-Dist: opentelemetry-instrumentation-asyncpg ==0.39b0
Requires-Dist: opentelemetry-instrumentation-boto ==0.39b0
Requires-Dist: opentelemetry-instrumentation-boto3sqs ==0.39b0
Requires-Dist: opentelemetry-instrumentation-botocore ==0.39b0
Requires-Dist: opentelemetry-instrumentation-celery ==0.39b0
Requires-Dist: opentelemetry-instrumentation-confluent-kafka ==0.39b0
Requires-Dist: opentelemetry-instrumentation-django ==0.39b0
Requires-Dist: opentelemetry-instrumentation-elasticsearch ==0.39b0
Requires-Dist: opentelemetry-instrumentation-falcon ==0.39b0
Requires-Dist: opentelemetry-instrumentation-fastapi ==0.39b0
Requires-Dist: opentelemetry-instrumentation-flask ==0.39b0
Requires-Dist: opentelemetry-instrumentation-grpc ==0.39b0
Requires-Dist: opentelemetry-instrumentation-httpx ==0.39b0
Requires-Dist: opentelemetry-instrumentation-jinja2 ==0.39b0
Requires-Dist: opentelemetry-instrumentation-kafka-python ==0.39b0
Requires-Dist: opentelemetry-instrumentation-mysql ==0.39b0
Requires-Dist: opentelemetry-instrumentation-pika ==0.39b0
Requires-Dist: opentelemetry-instrumentation-psycopg2 ==0.39b0
Requires-Dist: opentelemetry-instrumentation-pymemcache ==0.39b0
Requires-Dist: opentelemetry-instrumentation-pymongo ==0.39b0
Requires-Dist: opentelemetry-instrumentation-pymysql ==0.39b0
Requires-Dist: opentelemetry-instrumentation-pyramid ==0.39b0
Requires-Dist: opentelemetry-instrumentation-redis ==0.39b0
Requires-Dist: opentelemetry-instrumentation-remoulade ==0.39b0
Requires-Dist: opentelemetry-instrumentation-requests ==0.39b0
Requires-Dist: opentelemetry-instrumentation-sklearn ==0.39b0
Requires-Dist: opentelemetry-instrumentation-sqlalchemy ==0.39b0
Requires-Dist: opentelemetry-instrumentation-starlette ==0.39b0
Requires-Dist: opentelemetry-instrumentation-system-metrics ==0.39b0
Requires-Dist: opentelemetry-instrumentation-tornado ==0.39b0
Requires-Dist: opentelemetry-instrumentation-tortoiseorm ==0.39b0
Requires-Dist: opentelemetry-instrumentation-urllib3 ==0.39b0
Requires-Dist: antlr4-python3-runtime ==4.9.2
